{"list":[{"note":"W","timing":0.6006855964660645,"gameObject":{"instanceID":-2795908}},{"note":"W","timing":2.383915424346924,"gameObject":{"instanceID":-2809632}},{"note":"Q","timing":4.319231986999512,"gameObject":{"instanceID":-2813212}},{"note":"E","timing":6.09644889831543,"gameObject":{"instanceID":-2816624}},{"note":"W","timing":8.067861557006836,"gameObject":{"instanceID":-2842868}},{"note":"QW","timing":8.522849082946778,"gameObject":{"instanceID":-2847808}},{"note":"EW","timing":9.391403198242188,"gameObject":{"instanceID":-2849516}},{"note":"EW","timing":10.363058090209961,"gameObject":{"instanceID":-2851424}},{"note":"QW","timing":11.275827407836914,"gameObject":{"instanceID":-2853308}},{"note":"QW","timing":12.185439109802246,"gameObject":{"instanceID":-2855080}},{"note":"EW","timing":13.155134201049805,"gameObject":{"instanceID":-2856916}},{"note":"EW","timing":14.047944068908692,"gameObject":{"instanceID":-2858688}},{"note":"QW","timing":15.051559448242188,"gameObject":{"instanceID":-2860652}},{"note":"QW","timing":15.95605182647705,"gameObject":{"instanceID":-2862392}},{"note":"EW","timing":16.896657943725587,"gameObject":{"instanceID":-2864292}},{"note":"EW","timing":17.82538414001465,"gameObject":{"instanceID":-2866080}},{"note":"QW","timing":18.805347442626954,"gameObject":{"instanceID":-2867828}},{"note":"QW","timing":19.721349716186525,"gameObject":{"instanceID":-2869544}},{"note":"EW","timing":20.655405044555665,"gameObject":{"instanceID":-2871308}},{"note":"EW","timing":21.585193634033204,"gameObject":{"instanceID":-2873184}},{"note":"QW","timing":22.517555236816408,"gameObject":{"instanceID":-2874948}},{"note":"W","timing":23.058198928833009,"gameObject":{"instanceID":-2878784}},{"note":"W","timing":23.52495574951172,"gameObject":{"instanceID":-2882604}},{"note":"W","timing":24.38797378540039,"gameObject":{"instanceID":-2884264}},{"note":"Q","timing":25.33075523376465,"gameObject":{"instanceID":-2886124}},{"note":"E","timing":26.30030632019043,"gameObject":{"instanceID":-2887952}},{"note":"W","timing":27.191970825195314,"gameObject":{"instanceID":-2889652}},{"note":"Q","timing":28.15296173095703,"gameObject":{"instanceID":-2891560}},{"note":"W","timing":29.07632064819336,"gameObject":{"instanceID":-2893324}},{"note":"E","timing":30.06911277770996,"gameObject":{"instanceID":-2895256}},{"note":"E","timing":30.972652435302736,"gameObject":{"instanceID":-2897028}},{"note":"W","timing":31.915090560913087,"gameObject":{"instanceID":-2898816}},{"note":"Q","timing":32.813079833984378,"gameObject":{"instanceID":-2900516}},{"note":"Q","timing":33.7966423034668,"gameObject":{"instanceID":-2902416}},{"note":"W","timing":34.72085952758789,"gameObject":{"instanceID":-2904140}},{"note":"E","timing":35.687747955322269,"gameObject":{"instanceID":-2905992}},{"note":"W","timing":36.5854377746582,"gameObject":{"instanceID":-2907756}},{"note":"Q","timing":37.50439453125,"gameObject":{"instanceID":-2909504}},{"note":"W","timing":38.04180908203125,"gameObject":{"instanceID":-2931940}},{"note":"W","timing":41.7544059753418,"gameObject":{"instanceID":-2938744}},{"note":"Q","timing":46.42287826538086,"gameObject":{"instanceID":-2961960}},{"note":"W","timing":47.3718147277832,"gameObject":{"instanceID":-2963844}},{"note":"W","timing":48.27550506591797,"gameObject":{"instanceID":-2965552}},{"note":"E","timing":49.20947265625,"gameObject":{"instanceID":-2967308}},{"note":"Q","timing":50.16495895385742,"gameObject":{"instanceID":-2969192}},{"note":"W","timing":51.09996032714844,"gameObject":{"instanceID":-2970956}},{"note":"W","timing":52.01551055908203,"gameObject":{"instanceID":-2972696}},{"note":"Q","timing":53.53331756591797,"gameObject":{"instanceID":-2999840}},{"note":"W","timing":54.416805267333987,"gameObject":{"instanceID":-3001516}},{"note":"E","timing":55.3172607421875,"gameObject":{"instanceID":-3003232}},{"note":"W","timing":56.27015686035156,"gameObject":{"instanceID":-3005060}},{"note":"W","timing":57.2246208190918,"gameObject":{"instanceID":-3006864}},{"note":"W","timing":58.22657012939453,"gameObject":{"instanceID":-3008820}},{"note":"Q","timing":59.09740447998047,"gameObject":{"instanceID":-3010472}},{"note":"W","timing":60.03107452392578,"gameObject":{"instanceID":-3012220}},{"note":"EW","timing":60.96910858154297,"gameObject":{"instanceID":-3014040}},{"note":"QW","timing":61.91859436035156,"gameObject":{"instanceID":-3015852}},{"note":"QW","timing":62.835968017578128,"gameObject":{"instanceID":-3017568}},{"note":"EW","timing":63.7750129699707,"gameObject":{"instanceID":-3019412}},{"note":"QW","timing":64.6455078125,"gameObject":{"instanceID":-3021048}},{"note":"EW","timing":65.68768310546875,"gameObject":{"instanceID":-3023028}},{"note":"EW","timing":66.5726089477539,"gameObject":{"instanceID":-3024752}},{"note":"QWE","timing":67.05526733398438,"gameObject":{"instanceID":-3042180}},{"note":"QWE","timing":67.12651062011719,"gameObject":{"instanceID":-3042332}},{"note":"QWE","timing":67.1978759765625,"gameObject":{"instanceID":-3042492}},{"note":"QWE","timing":67.27022552490235,"gameObject":{"instanceID":-3042644}},{"note":"QWE","timing":67.34258270263672,"gameObject":{"instanceID":-3042812}},{"note":"QWE","timing":67.4162368774414,"gameObject":{"instanceID":-3042972}},{"note":"QWE","timing":67.48890686035156,"gameObject":{"instanceID":-3043140}},{"note":"QWE","timing":67.56285858154297,"gameObject":{"instanceID":-3043300}},{"note":"QWE","timing":67.63460540771485,"gameObject":{"instanceID":-3043460}},{"note":"QWE","timing":67.70865631103516,"gameObject":{"instanceID":-3043612}},{"note":"QWE","timing":67.78223419189453,"gameObject":{"instanceID":-3043780}},{"note":"QWE","timing":67.85572814941406,"gameObject":{"instanceID":-3043932}},{"note":"QWE","timing":67.92678833007813,"gameObject":{"instanceID":-3044092}},{"note":"QWE","timing":67.99678802490235,"gameObject":{"instanceID":-3044244}},{"note":"QWE","timing":68.07243347167969,"gameObject":{"instanceID":-3044348}},{"note":"W","timing":71.7398452758789,"gameObject":{"instanceID":-3051148}},{"note":"E","timing":73.63655090332031,"gameObject":{"instanceID":-3054608}}]}
